LICENSE
MANIFEST.in
README.md
requirements.txt
setup.py
moomoo/VERSION.txt
moomoo/__init__.py
moomoo/common/__init__.py
moomoo/common/callback_executor.py
moomoo/common/comm_add_path.py
moomoo/common/conn_key.txt
moomoo/common/conn_mng.py
moomoo/common/constant.py
moomoo/common/err.py
moomoo/common/ft_logger.py
moomoo/common/handler_context.py
moomoo/common/network_manager.py
moomoo/common/open_context_base.py
moomoo/common/pbjson.py
moomoo/common/sys_config.py
moomoo/common/utils.py
moomoo/common/pb/Common.proto
moomoo/common/pb/Common_pb2.py
moomoo/common/pb/GetDelayStatistics.proto
moomoo/common/pb/GetDelayStatistics_pb2.py
moomoo/common/pb/GetGlobalState.proto
moomoo/common/pb/GetGlobalState_pb2.py
moomoo/common/pb/GetUserInfo.proto
moomoo/common/pb/GetUserInfo_pb2.py
moomoo/common/pb/InitConnect.proto
moomoo/common/pb/InitConnect_pb2.py
moomoo/common/pb/KeepAlive.proto
moomoo/common/pb/KeepAlive_pb2.py
moomoo/common/pb/Notify.proto
moomoo/common/pb/Notify_pb2.py
moomoo/common/pb/Qot_Common.proto
moomoo/common/pb/Qot_Common_pb2.py
moomoo/common/pb/Qot_GetBasicQot.proto
moomoo/common/pb/Qot_GetBasicQot_pb2.py
moomoo/common/pb/Qot_GetBroker.proto
moomoo/common/pb/Qot_GetBroker_pb2.py
moomoo/common/pb/Qot_GetCapitalDistribution.proto
moomoo/common/pb/Qot_GetCapitalDistribution_pb2.py
moomoo/common/pb/Qot_GetCapitalFlow.proto
moomoo/common/pb/Qot_GetCapitalFlow_pb2.py
moomoo/common/pb/Qot_GetCodeChange.proto
moomoo/common/pb/Qot_GetCodeChange_pb2.py
moomoo/common/pb/Qot_GetFutureInfo.proto
moomoo/common/pb/Qot_GetFutureInfo_pb2.py
moomoo/common/pb/Qot_GetHistoryKL.proto
moomoo/common/pb/Qot_GetHistoryKLPoints.proto
moomoo/common/pb/Qot_GetHistoryKLPoints_pb2.py
moomoo/common/pb/Qot_GetHistoryKL_pb2.py
moomoo/common/pb/Qot_GetHoldingChangeList.proto
moomoo/common/pb/Qot_GetHoldingChangeList_pb2.py
moomoo/common/pb/Qot_GetIpoList.proto
moomoo/common/pb/Qot_GetIpoList_pb2.py
moomoo/common/pb/Qot_GetKL.proto
moomoo/common/pb/Qot_GetKL_pb2.py
moomoo_api.egg-info/PKG-INFO
moomoo_api.egg-info/SOURCES.txt
moomoo_api.egg-info/dependency_links.txt
moomoo_api.egg-info/requires.txt
moomoo_api.egg-info/top_level.txt