Metadata-Version: 2.1
Name: moomoo-api
Version: 9.4.5408
Summary: Moomoo Quantitative Trading API
Home-page: https://github.com/MoomooOpen/py-moomoo-api
Author: Moomoo, Inc.
Author-email: openapi@moomoo.com
License: Apache License 2.0
Keywords: Moomoo Stock Quant Trading API
License-File: LICENSE
